<?xml version="1.0"?>
<asset assetType="sceneObject" changesEnabled="Disabled">
	<!--comics: 2-->
	<!--effectBehaviour: 1-->
	<!--fixes: 5-->
	<!--gears: 1-->
	<!--m3c: 29-->
	<!--physics: 2-->
	<!--quests: 1-->
	<!--roomDesign: 7-->
	<!--vso: 69-->
	<!--windowManagement: 2-->
	<!--ws: 7-->
	<!--wsGround: 3-->
	<!--wsGroupAnimationController: 1-->
	<!--wsInteractiveScene: 1-->
	<!--wsMainHUDItemEffect: 1-->
	<!--wsQuiz: 1-->
	<!--wsSceneObjectRef: 19-->
	<root name="20_binoculars">
		<behaviours type="anchoredElement">
			<ptr autoAttachToParent="true">
				<horizontalAnchor nrp_1="0.5" />
				<uid entityId="2760923012" />
				<verticalAnchor nrp_1="0.5" />
			</ptr>
		</behaviours>
		<children name="img_0" visibility="false">
			<behaviours type="anchoredElement">
				<ptr autoAttachToParent="true">
					<horizontalAnchor nrp_1="0.5" />
					<normalizedPivot x="0.5" y="0.5" />
					<uid entityId="525422350" />
					<verticalAnchor nrp_1="0.5" />
				</ptr>
			</behaviours>
			<transform />
			<uid entityId="3364506314" />
		</children>
		<transform />
		<uid entityId="3036706651" />
	</root>
</asset>
